cc_sphinx_changelog/__init__.py
cc_sphinx_changelog/cc_sphinx_changelog.py
cc_sphinx_changelog-0.6.1.dist-info/LICENSE
cc_sphinx_changelog-0.6.1.dist-info/METADATA
cc_sphinx_changelog-0.6.1.dist-info/WHEEL
cc_sphinx_changelog-0.6.1.dist-info/top_level.txt
cc_sphinx_changelog-0.6.1.dist-info/RECORD
