Metadata-Version: 2.1
Name: cc-sphinx-changelog
Version: 0.6.1
Summary: Automatically generates a releases-style changelog based on conventional commit messages.
Home-page: https://github.com/pgierz/cc_sphinx_changelog
Author: Paul Gierz
Author-email: pgierz@awi.de
License: GNU General Public License v3
Keywords: cc_sphinx_changelog
Platform: UNKNOWN
Classifier: Development Status :: 2 - Pre-Alpha
Classifier: Intended Audience :: Developers
Classifier: License :: OSI Approved :: GNU General Public License v3 (GPLv3)
Classifier: Natural Language :: English
Classifier: Programming Language :: Python :: 3.6
Classifier: Programming Language :: Python :: 3.7
Classifier: Programming Language :: Python :: 3.8
Classifier: Programming Language :: Python :: 3.9
Requires-Dist: gitpython
Requires-Dist: backpedal
Requires-Dist: ansiwrap
Requires-Dist: crayons
Requires-Dist: docutils
Requires-Dist: sphinx
